[
  {
    "img": "_nuxt/assets/img/1.png",
    "title": "Неограниченый автопарк",
    "descr": "Можно добавить неограниченное кол-во машин и водителей",
    "id": 0
  },
  {
    "img": "_nuxt/assets/img/2.png",
    "title": "Сокращение затрат до 50%",
    "descr": "Максимально быстро узнаете о штрафах в автоматическом режиме, тем самым у вас есть время оплатить по скидке",
    "id": 1
  },
  {
    "img": "_nuxt/assets/img/3.png",
    "title": "Безопасность",
    "descr": "Данные передаются в зашифрованном виде, они доступны только получателю",
    "id": 2
  },
  {
    "img": "_nuxt/assets/img/4.png",
    "title": "Уведомление о погашении",
    "descr": "Мы оповестим вас о том, что штраф был погашен и соответствующая запись создана в ГИС ГМП",
    "id": 3
  },
  {
    "img": "_nuxt/assets/img/5.png",
    "title": "Квитанция об оплате",
    "descr": "После совершения оплаты банковской картой на Вашу электронную почту придет квитанция об успешной оплате.",
    "id": 4
  },
  {
    "img": "_nuxt/assets/img/6.png",
    "title": "Все история сохраняется по каждой машине",
    "descr": "Вся история штрафов сохраняется по машине и водителю, позволяет анализировать статистику по штрафам",
    "id": 5
  }
]
